RustShijianZhinanFix1/README.md
RustShijianZhinanFix1/__init__.py
RustShijianZhinanFix1/__main__.py
RustShijianZhinanFix1/file.epub
RustShijianZhinanFix1/index.html
RustShijianZhinanFix1/css/__init__.py
RustShijianZhinanFix1/css/annotations.css
RustShijianZhinanFix1/css/main.css
RustShijianZhinanFix1/css/normalize.css
RustShijianZhinanFix1/css/popup.css
RustShijianZhinanFix1/font/__init__.py
RustShijianZhinanFix1/font/fontello.eot
RustShijianZhinanFix1/font/fontello.svg
RustShijianZhinanFix1/font/fontello.ttf
RustShijianZhinanFix1/font/fontello.woff
RustShijianZhinanFix1/img/__init__.py
RustShijianZhinanFix1/img/annotator-glyph-sprite.png
RustShijianZhinanFix1/img/annotator-icon-sprite.png
RustShijianZhinanFix1/img/apple-touch-icon.png
RustShijianZhinanFix1/img/cancelfullscreen.png
RustShijianZhinanFix1/img/close.png
RustShijianZhinanFix1/img/fullscreen.png
RustShijianZhinanFix1/img/loader.gif
RustShijianZhinanFix1/img/menu-icon.png
RustShijianZhinanFix1/img/save.png
RustShijianZhinanFix1/img/saved.png
RustShijianZhinanFix1/img/settings-s.png
RustShijianZhinanFix1/img/settings.png
RustShijianZhinanFix1/img/star.png
RustShijianZhinanFix1/js/__init__.py
RustShijianZhinanFix1/js/epub.js
RustShijianZhinanFix1/js/epub.min.js
RustShijianZhinanFix1/js/epub.min.map
RustShijianZhinanFix1/js/hooks.min.js
RustShijianZhinanFix1/js/hooks.min.map
RustShijianZhinanFix1/js/reader.js
RustShijianZhinanFix1/js/reader.js.map
RustShijianZhinanFix1/js/reader.min.js
RustShijianZhinanFix1/js/reader.min.map
RustShijianZhinanFix1/js/hooks/__init__.py
RustShijianZhinanFix1/js/hooks/extensions/__init__.py
RustShijianZhinanFix1/js/hooks/extensions/highlight.js
RustShijianZhinanFix1/js/libs/__init__.py
RustShijianZhinanFix1/js/libs/jquery.min.js
RustShijianZhinanFix1/js/libs/localforage.min.js
RustShijianZhinanFix1/js/libs/screenfull.js
RustShijianZhinanFix1/js/libs/screenfull.min.js
RustShijianZhinanFix1/js/libs/zip.min.js
RustShijianZhinanFix1/js/plugins/__init__.py
rust_shijian_zhinan_fix1-2025.3.25.1.dist-info/METADATA
rust_shijian_zhinan_fix1-2025.3.25.1.dist-info/WHEEL
rust_shijian_zhinan_fix1-2025.3.25.1.dist-info/entry_points.txt
rust_shijian_zhinan_fix1-2025.3.25.1.dist-info/top_level.txt
rust_shijian_zhinan_fix1-2025.3.25.1.dist-info/RECORD
